chinta/__init__.py
chinta/chinta.py
chinta-1.0.2.dist-info/licenses/LICENSE
chinta-1.0.2.dist-info/METADATA
chinta-1.0.2.dist-info/WHEEL
chinta-1.0.2.dist-info/entry_points.txt
chinta-1.0.2.dist-info/top_level.txt
chinta-1.0.2.dist-info/RECORD
