Metadata-Version: 2.4
Name: chinta
Version: 1.0.2
Summary: Tex Repository Word Counter
Author-email: Max Hughson <max.ak.hughson+pypitest@gmail.com>
Keywords: latex,tex,thesis
Classifier: Programming Language :: Python :: 3
Classifier: Operating System :: OS Independent
Requires-Python: >=3
License-File: LICENSE
Requires-Dist: GitPython
Requires-Dist: matplotlib
Dynamic: license-file
